competencia_mexico/__init__.py
competencia_mexico/articulos.py
competencia_mexico/graficos.py
competencia_mexico/indices.py
competencia_mexico/modelos.py
competencia_mexico/rag.py
competencia_mexico/sobreprecios.py
competencia_mexico/data/articulos_final.csv
competencia_mexico/data/estadisticas_final.csv
competencia_mexico/data/faiss_index/faiss_index.pkl
competencia_mexico/data/faiss_index/index.faiss
competencia_mexico/data/faiss_index/index.pkl
competencia_mexico/data/faiss_index/t.txt
competencia_mexico-0.1.5.dist-info/licenses/LICENSE
competencia_mexico-0.1.5.dist-info/METADATA
competencia_mexico-0.1.5.dist-info/WHEEL
competencia_mexico-0.1.5.dist-info/top_level.txt
competencia_mexico-0.1.5.dist-info/RECORD
