Metadata-Version: 2.4
Name: competencia_mexico
Version: 0.1.5
Summary: Herramientas para análisis de competencia económica, precios, visualización y RAG (FAISS + DeepSeek)
Home-page: https://github.com/IvanParedesR/competencia_mexico
Author: Iván Paredes Reséndiz
Author-email: Iván Paredes Reséndiz <ivanresendiz25@gmail.com>
License: MIT License
Requires-Python: >=3.8
License-File: LICENSE
Requires-Dist: pandas>=1.3
Requires-Dist: numpy>=1.21
Requires-Dist: matplotlib>=3.5
Requires-Dist: requests>=2.28
Requires-Dist: langchain-community>=0.2.0
Requires-Dist: sentence-transformers>=2.5.0
Requires-Dist: faiss-cpu>=1.7.4
Requires-Dist: importlib-resources>=5.12; python_version < "3.9"
Provides-Extra: dev
Requires-Dist: pytest; extra == "dev"
Requires-Dist: black; extra == "dev"
Requires-Dist: ruff; extra == "dev"
Requires-Dist: twine; extra == "dev"
Requires-Dist: build; extra == "dev"
Dynamic: author
Dynamic: home-page
Dynamic: license-file
Dynamic: requires-python
